edx_event_bus_kafka/__init__.py
edx_event_bus_kafka/apps.py
edx_event_bus_kafka/models.py
edx_event_bus_kafka/urls.py
edx_event_bus_kafka/internal/__init__.py
edx_event_bus_kafka/internal/config.py
edx_event_bus_kafka/internal/consumer.py
edx_event_bus_kafka/internal/producer.py
edx_event_bus_kafka/internal/utils.py
edx_event_bus_kafka/internal/tests/__init__.py
edx_event_bus_kafka/internal/tests/test_config.py
edx_event_bus_kafka/internal/tests/test_consumer.py
edx_event_bus_kafka/internal/tests/test_producer.py
edx_event_bus_kafka/internal/tests/test_utils.py
edx_event_bus_kafka/management/__init__.py
edx_event_bus_kafka/management/commands/__init__.py
edx_event_bus_kafka/management/commands/produce_event.py
edx_event_bus_kafka/templates/edx_event_bus_kafka/base.html
edx_event_bus_kafka-6.1.0.dist-info/licenses/LICENSE.txt
edx_event_bus_kafka-6.1.0.dist-info/METADATA
edx_event_bus_kafka-6.1.0.dist-info/WHEEL
edx_event_bus_kafka-6.1.0.dist-info/top_level.txt
edx_event_bus_kafka-6.1.0.dist-info/RECORD
