Metadata-Version: 2.4
Name: edx_event_bus_kafka
Version: 6.1.0
Summary: Kafka implementation for Open edX event bus.
Home-page: https://github.com/openedx/event-bus-kafka
Author: edX
Author-email: oscm@edx.org
License: AGPL 3.0
Keywords: Python edx
Classifier: Development Status :: 3 - Alpha
Classifier: Framework :: Django
Classifier: Framework :: Django :: 4.2
Classifier: Framework :: Django :: 5.2
Classifier: Intended Audience :: Developers
Classifier: License :: OSI Approved :: GNU Affero General Public License v3 or later (AGPLv3+)
Classifier: Natural Language :: English
Classifier: Programming Language :: Python :: 3
Classifier: Programming Language :: Python :: 3.12
Requires-Python: >=3.8
License-File: LICENSE.txt
Requires-Dist: Django
Requires-Dist: edx_django_utils
Requires-Dist: edx_toggles
Requires-Dist: openedx-events>=9.3.0
Dynamic: author
Dynamic: author-email
Dynamic: classifier
Dynamic: description
Dynamic: home-page
Dynamic: keywords
Dynamic: license
Dynamic: license-file
Dynamic: requires-dist
Dynamic: requires-python
Dynamic: summary
